ansible/module_utils/morpheus.py
ansible/modules/morpheus/__init__.py
ansible/modules/morpheus/morph_cypher.py
ansible/plugins/lookup/morph_cypher.py
ansible_modules_morpheus-0.2.0.dist-info/AUTHORS
ansible_modules_morpheus-0.2.0.dist-info/LICENSE
ansible_modules_morpheus-0.2.0.dist-info/METADATA
ansible_modules_morpheus-0.2.0.dist-info/WHEEL
ansible_modules_morpheus-0.2.0.dist-info/top_level.txt
ansible_modules_morpheus-0.2.0.dist-info/RECORD
