Metadata-Version: 2.1
Name: ansible-modules-morpheus
Version: 0.2.0
Summary: Ansible Modules for Morpheus Data
Home-page: https://github.com/gomorpheus/ansible-modules-morpheus
Author: Adam Hicks
Author-email: ahicks@morpheusdata.com
License: UNKNOWN
Platform: UNKNOWN
Requires-Dist: ansible (>=2.0.0)
Requires-Dist: requests (>=2.21.0)
